Geom8ry/__init__.py
Geom8ry/circle.py
Geom8ry/constants.py
Geom8ry/delaunay.py
Geom8ry/dft.py
Geom8ry/ellipse.py
Geom8ry/exceptions.py
Geom8ry/graph.py
Geom8ry/hull.py
Geom8ry/hyperbola.py
Geom8ry/idft.py
Geom8ry/line.py
Geom8ry/matrix.py
Geom8ry/parabola.py
Geom8ry/point.py
Geom8ry/polygon.py
Geom8ry/polynomial.py
Geom8ry/rectangle.py
Geom8ry/regularpolygon.py
Geom8ry/segment.py
Geom8ry/tempCodeRunnerFile.py
Geom8ry/test.py
Geom8ry/triangle.py
Geom8ry/vector.py
Geom8ry-0.0.1.dist-info/LICENSE
Geom8ry-0.0.1.dist-info/METADATA
Geom8ry-0.0.1.dist-info/WHEEL
Geom8ry-0.0.1.dist-info/top_level.txt
Geom8ry-0.0.1.dist-info/RECORD
