Metadata-Version: 2.1
Name: Geom8ry
Version: 0.0.1
Summary: Geom8ry the python way.
Home-page: https://github.com/raje-ev/Geom8ry
Author: Rajeev Kumar
Author-email: rajeevkumar.nitp@gmail.com
License: MIT
Project-URL: Bug Tracker, https://github.com/raje-ev/Geom8ry/issues
Keywords: Geom8ry point circle line line segment triangle rectangle graph fft dft triangulation
Platform: UNKNOWN
Classifier: Development Status :: 2 - Pre-Alpha
Classifier: Intended Audience :: Education
Classifier: Topic :: Software Development :: Libraries :: Python Modules
Classifier: Topic :: Scientific/Engineering :: Mathematics
Classifier: License :: OSI Approved :: MIT License
Classifier: Programming Language :: Python :: 3
Classifier: Programming Language :: Python :: 3.6
Classifier: Operating System :: OS Independent
Requires-Python: >=3.6
